trussty/__init__.py
trussty/mesh.py
trussty/support_markers.py
trussty-0.1.1.dist-info/LICENSE
trussty-0.1.1.dist-info/METADATA
trussty-0.1.1.dist-info/WHEEL
trussty-0.1.1.dist-info/top_level.txt
trussty-0.1.1.dist-info/RECORD
