Metadata-Version: 2.1
Name: trussty
Version: 0.1.1
Summary: python package to analyse trusses
Author: Levi Rogalla
License: MIT
Classifier: Programming Language :: Python :: 3
Classifier: Programming Language :: Python :: 3.10
Classifier: Operating System :: OS Independent
Requires-Python: >=3.9
License-File: LICENSE
Requires-Dist: matplotlib ==3.7.2
Requires-Dist: torch ==2.0.1
Requires-Dist: tqdm ==4.65.0
Requires-Dist: pandas ==2.0.3
